nllgrid/NLLGrid.py
nllgrid/__init__.py
nllgrid/_version.py
nllgrid/ellipsoid.py
nllgrid-1.6.dist-info/licenses/LICENSE.txt
nllgrid-1.6.dist-info/METADATA
nllgrid-1.6.dist-info/WHEEL
nllgrid-1.6.dist-info/top_level.txt
nllgrid-1.6.dist-info/RECORD
