Metadata-Version: 2.4
Name: nllgrid
Version: 1.6
Summary: Python class for reading and writing NonLinLoc grid files
Author-email: Claudio Satriano <satriano@ipgp.fr>
License: GNU General Public License v3 or later (GPLv3+)
Project-URL: Homepage, https://github.com/claudiodsf/nllgrid
Platform: OS
Platform: Independent
Classifier: Development Status :: 5 - Production/Stable
Classifier: Environment :: Console
Classifier: Intended Audience :: Science/Research
Classifier: License :: OSI Approved :: GNU General Public License v3 or later (GPLv3+)
Classifier: Operating System :: OS Independent
Classifier: Programming Language :: Python
Classifier: Programming Language :: Python :: 3
Classifier: Programming Language :: Python :: 3.8
Classifier: Programming Language :: Python :: 3.9
Classifier: Programming Language :: Python :: 3.10
Classifier: Programming Language :: Python :: 3.11
Classifier: Programming Language :: Python :: 3.12
Classifier: Programming Language :: Python :: 3.13
Classifier: Topic :: Scientific/Engineering
Classifier: Topic :: Scientific/Engineering :: Physics
Requires-Python: >=3.8
License-File: LICENSE.txt
Requires-Dist: numpy>=1.0
Requires-Dist: scipy>=0.16
Requires-Dist: pyproj
Dynamic: description
Dynamic: description-content-type
Dynamic: license-file
